XStatic_svgweb-2011.2.3.2-py3.13-nspkg.pth
xstatic/pkg/svgweb/__init__.py
xstatic/pkg/svgweb/data/svg-uncompressed.htc
xstatic/pkg/svgweb/data/svg-uncompressed.js
xstatic/pkg/svgweb/data/svg.htc
xstatic/pkg/svgweb/data/svg.js
xstatic/pkg/svgweb/data/svg.swf
xstatic_svgweb-2011.2.3.2.dist-info/METADATA
xstatic_svgweb-2011.2.3.2.dist-info/WHEEL
xstatic_svgweb-2011.2.3.2.dist-info/namespace_packages.txt
xstatic_svgweb-2011.2.3.2.dist-info/top_level.txt
xstatic_svgweb-2011.2.3.2.dist-info/RECORD
