Metadata-Version: 2.4
Name: XStatic-svgweb
Version: 2011.2.3.2
Summary: svgweb 2011.2.3 (XStatic packaging standard)
Home-page: http://code.google.com/p/svgweb/
Maintainer: Thomas Waldmann
Maintainer-email: tw@waldmann-edv.de
License: (same as svgweb)
Keywords: svgweb xstatic
Platform: any
Dynamic: description
Dynamic: home-page
Dynamic: keywords
Dynamic: license
Dynamic: maintainer
Dynamic: maintainer-email
Dynamic: platform
Dynamic: summary
